cliffs_delta/__init__.py
cliffs_delta/test_cliff.py
cliffs_delta-1.0.0.dist-info/LICENSE
cliffs_delta-1.0.0.dist-info/METADATA
cliffs_delta-1.0.0.dist-info/WHEEL
cliffs_delta-1.0.0.dist-info/top_level.txt
cliffs_delta-1.0.0.dist-info/RECORD
