Metadata-Version: 2.1
Name: cliffs-delta
Version: 1.0.0
Summary: Python Package to calculate Cliff's delta
Home-page: https://github.com/neilernst/cliffsDelta
Author: neilernst/prkhrv
Author-email: neil@neilernst.net
License: MIT
Platform: UNKNOWN
Classifier: License :: OSI Approved :: MIT License
Classifier: Programming Language :: Python :: 3
Classifier: Programming Language :: Python :: 3.7
